{
  "A": {
    "image": "cell1.png",
    "active": false,
    "activationImage": "cell1-fill.png",
    "activation": 8,
    "score": 1
  },
  "B": {
    "image": "cell2.png",
    "active": false
  },
  "C": {
    "image": "cell4.png",
    "active": false,
    "activationImage": "cell4-fill.png",
    "activation": 22,
    "score": 3
  },
  "IC": {
    "activationImage": "islandC.png",
    "active": true,
    "playerDir": "top",
    "action": "history",
    "activation": 0
  },
  "ITL": {
    "activationImage": "islandTL.png",
    "active": true,
    "playerDir": "top"
  },
  "IT": {
    "activationImage": "islandT.png",
    "active": true,
    "playerDir": "top"
  },
  "ITR": {
    "activationImage": "islandTR.png",
    "active": true,
    "playerDir": "top"
  },
  "IR": {
    "activationImage": "islandR.png",
    "active": true,
    "action": "history",
    "playerDir": "top"
  },
  "IBR": {
    "activationImage": "islandBR.png",
    "active": true,
    "playerDir": "top"
  },
  "IB": {
    "activationImage": "islandB.png",
    "active": true,
    "playerDir": "top"
  },
  "IBL": {
    "activationImage": "islandBL.png",
    "active": true,
    "playerDir": "top"
  },
  "IL": {
    "activationImage": "islandL.png",
    "active": true,
    "playerDir": "top",
    "action": "history",
    "activation": 0
  }
}
